pypomes_soap/__init__.py
pypomes_soap/soap_pomes.py
pypomes_soap-0.2.7.dist-info/METADATA
pypomes_soap-0.2.7.dist-info/WHEEL
pypomes_soap-0.2.7.dist-info/licenses/LICENSE
pypomes_soap-0.2.7.dist-info/RECORD
