Metadata-Version: 2.4
Name: pypomes_soap
Version: 0.2.7
Summary: A collection of Python pomes, penyeach (SOAP module)
Project-URL: Homepage, https://github.com/TheWiseCoder/PyPomes-SOAP
Project-URL: Bug Tracker, https://github.com/TheWiseCoder/PyPomes-SOAP/issues
Author-email: GT Nunes <wisecoder01@gmail.com>
License-File: LICENSE
Classifier: License :: OSI Approved :: MIT License
Classifier: Operating System :: OS Independent
Classifier: Programming Language :: Python :: 3
Requires-Python: >=3.14
Requires-Dist: lxml>=6.0.2
Requires-Dist: pypomes-core>=2.9.4
Requires-Dist: requests>=2.32.5
Requires-Dist: zeep>=4.3.2
